README.rst
codapress.zip
screenshot.png
setup.py
docs/HISTORY.txt
docs/INSTALL.txt
docs/LICENSE.GPL
docs/LICENSE.txt
plonetheme/__init__.py
plonetheme.codapress.egg-info/PKG-INFO
plonetheme.codapress.egg-info/SOURCES.txt
plonetheme.codapress.egg-info/dependency_links.txt
plonetheme.codapress.egg-info/entry_points.txt
plonetheme.codapress.egg-info/namespace_packages.txt
plonetheme.codapress.egg-info/requires.txt
plonetheme.codapress.egg-info/top_level.txt
plonetheme/codapress/__init__.py
plonetheme/codapress/configure.zcml
plonetheme/codapress/profiles/default/metadata.xml
plonetheme/codapress/profiles/default/theme.xml
plonetheme/codapress/static/index.html
plonetheme/codapress/static/license.txt
plonetheme/codapress/static/manifest.cfg
plonetheme/codapress/static/rules.xml
plonetheme/codapress/static/css/main.css
plonetheme/codapress/static/css/plone.css
plonetheme/codapress/static/css/skin.css
plonetheme/codapress/static/design/bg.png
plonetheme/codapress/static/design/footer.png
plonetheme/codapress/static/design/ico-rss.png
plonetheme/codapress/static/design/ico-twitter.png
plonetheme/codapress/static/design/nav-separator.png
plonetheme/codapress/static/design/nav.png
plonetheme/codapress/static/design/search-submit.png
plonetheme/codapress/static/design/section.png
plonetheme/codapress/static/design/tag.png
plonetheme/codapress/static/design/title.png
plonetheme/codapress/static/design/topstory.png
plonetheme/codapress/static/design/tray.png
plonetheme/codapress/static/design/ul.gif
plonetheme/codapress/static/javascript/cufon-yui.js
plonetheme/codapress/static/javascript/font.font.js
plonetheme/codapress/static/javascript/pngfix.js
plonetheme/codapress/static/tmp/125x125.gif
plonetheme/codapress/static/tmp/about-01.jpg
plonetheme/codapress/static/tmp/article-01.jpg
plonetheme/codapress/static/tmp/articles-01.jpg
plonetheme/codapress/static/tmp/articles-02.jpg
plonetheme/codapress/static/tmp/articles-03.jpg
plonetheme/codapress/static/tmp/articles-04.jpg
plonetheme/codapress/static/tmp/gallery-01.jpg
plonetheme/codapress/static/tmp/gallery-02.jpg
plonetheme/codapress/static/tmp/gallery-03.jpg
plonetheme/codapress/static/tmp/topstory.jpg